cuttle/__init__.py
cuttle/cli.py
cuttle/cuttleengine.py
cuttle/platform/linux/main.py
cuttle/transform/airflow/main.py
cuttle/transform/flask/README.md
cuttle/transform/flask/main.py
cuttle/transform/script/main.py
test/__init__.py
test/test_cuttleengine.py
cuttle-0.4.2.dist-info/LICENSE.txt
cuttle-0.4.2.dist-info/METADATA
cuttle-0.4.2.dist-info/WHEEL
cuttle-0.4.2.dist-info/entry_points.txt
cuttle-0.4.2.dist-info/top_level.txt
cuttle-0.4.2.dist-info/RECORD
