Metadata-Version: 2.1
Name: cuttle
Version: 0.4.2
Summary: UNKNOWN
Home-page: UNKNOWN
Author: Karishnu Poddar
Author-email: karishnu@gmail.com
License: UNKNOWN
Platform: UNKNOWN
Requires-Dist: Click
Requires-Dist: paramiko
Requires-Dist: scp
Requires-Dist: nbformat
Requires-Dist: nbconvert
Requires-Dist: ipython
Requires-Dist: click-log
